edx_api_doc_tools/__init__.py
edx_api_doc_tools/apps.py
edx_api_doc_tools/conf_utils.py
edx_api_doc_tools/data.py
edx_api_doc_tools/internal_utils.py
edx_api_doc_tools/urls.py
edx_api_doc_tools/view_utils.py
edx_api_doc_tools-2.1.2.dist-info/licenses/LICENSE.txt
edx_api_doc_tools-2.1.2.dist-info/METADATA
edx_api_doc_tools-2.1.2.dist-info/WHEEL
edx_api_doc_tools-2.1.2.dist-info/top_level.txt
edx_api_doc_tools-2.1.2.dist-info/RECORD
