Metadata-Version: 2.4
Name: edx-api-doc-tools
Version: 2.1.2
Summary: Tools for writing and generating API documentation for edX REST APIs
Home-page: https://github.com/openedx/api-doc-tools
Author: Open edX Project
Author-email: oscm@openedx.org
License: Apache Software License 2.0
Keywords: Django edx
Classifier: Development Status :: 3 - Alpha
Classifier: Framework :: Django
Classifier: Framework :: Django :: 4.2
Classifier: Framework :: Django :: 5.2
Classifier: Intended Audience :: Developers
Classifier: License :: OSI Approved :: Apache Software License
Classifier: Natural Language :: English
Classifier: Programming Language :: Python :: 3
Classifier: Programming Language :: Python :: 3.11
Classifier: Programming Language :: Python :: 3.12
License-File: LICENSE.txt
Requires-Dist: Django
Requires-Dist: djangorestframework>=3.2.0
Requires-Dist: drf-yasg
Requires-Dist: setuptools
Dynamic: author
Dynamic: author-email
Dynamic: classifier
Dynamic: description
Dynamic: description-content-type
Dynamic: home-page
Dynamic: keywords
Dynamic: license
Dynamic: license-file
Dynamic: requires-dist
Dynamic: summary
